{
  "projectName": "shell",
  "plugins": {
    "@release-it/bumper": { "in": "./version.json" },
    "@release-it/conventional-changelog": {
      "preset": "angular",
      "path": "."
    }
  },
  "git": {
    "tagName": "shell-v${version}",
    "tagMatch": "shell-v*",
    "commitsPath": ".",
    "commitMessage": "chore(shell): release v${version}"
  },
  "prePush": "",
  "github": {
    "release": true,
    "draft": true,
    "autoGenerate": true,
    "releaseName": "shell v${version}"
  }
}
